<?xml version="1.0" encoding="utf-8"?>
<root>
	<status>success</status>
	<message>The SDG_INDICATOR field for indicator 2-2-2, translated into all languages</message>
	<data>
		<languages>
			<language lang="en">&lt;p&gt;2.2.2 Prevalence of malnutrition (weight for height &gt;+2 or &lt;-2 standard deviation from the median of the WHO Child Growth Standards) among children under 5 years of age, by type (wasting and overweight)&lt;/p&gt;
			</language>
			<language lang="km">&lt;p&gt; ២.២.២ អត្រាប្រេវ៉ាឡង់នៃកង្វះអាហារូបត្ថម្ភ (ទំងន់កម្ពស់&gt; +២ ឬគម្លាតគំរូពីកំរិតមធ្យមនៃស្តង់ដារលូតលាស់របស់អង្គការសុខភាពពិភពលោក) ក្នុងចំណោមកុមារអាយុក្រោម ៥ ឆ្នាំតាមប្រភេទ (ខ្ជះខ្ជាយនិងលើសទម្ងន់) &lt;/p&gt; &gt;
			</language>
</languages>
</data>
</root>
